coolfunc/__init__.py
coolfunc/_core.py
coolfunc-1.1.4.dist-info/LICENSE
coolfunc-1.1.4.dist-info/WHEEL
coolfunc-1.1.4.dist-info/METADATA
coolfunc-1.1.4.dist-info/RECORD
