Metadata-Version: 2.1
Name: coolfunc
Version: 1.1.4
Summary: 一些小功能的集合
Keywords: coolfunc
Author-email: "lcctoor.com" <lcctoor@outlook.com>
Requires-Python: >=3.7
Classifier: License :: OSI Approved :: Apache Software License
Requires-Dist: vtype
Project-URL: HomePage, https://lcctoor.github.io/lccpy/?package=coolfunc
